CHANGELOG.txt
LICENSE.txt
MANIFEST.in
README.txt
setup.py
taitbasiccalculator/__init__.py
taitbasiccalculator.egg-info/PKG-INFO
taitbasiccalculator.egg-info/SOURCES.txt
taitbasiccalculator.egg-info/dependency_links.txt
taitbasiccalculator.egg-info/top_level.txt